MANIFEST.in
README.rst
requirements.txt
setup.py
django_s3backup.egg-info/PKG-INFO
django_s3backup.egg-info/SOURCES.txt
django_s3backup.egg-info/dependency_links.txt
django_s3backup.egg-info/requires.txt
django_s3backup.egg-info/top_level.txt
s3backup/__init__.py
s3backup/models.py
s3backup/management/__init__.py
s3backup/management/commands/__init__.py
s3backup/management/commands/backup_to_s3.py