Metadata-Version: 1.0
Name: django-s3backup
Version: 1.0.2
Summary: A django app to backup database dumps to an S3 bucket
Home-page: https://bitbucket.org/tino/django-s3backup/
Author: Tino de Bruijn
Author-email: tinodb@gmail.com
License: UNKNOWN
Platform: UNKNOWN
Classifier: Development Status :: 4 - Beta
Classifier: Environment :: Web Environment
Classifier: Framework :: Django
Classifier: Intended Audience :: Developers
Classifier: License :: OSI Approved :: MIT License
Classifier: Operating System :: OS Independent
Classifier: Programming Language :: Python
Classifier: Programming Language :: Python :: 2.5
Classifier: Programming Language :: Python :: 2.6
Classifier: Programming Language :: Python :: 2.7
Classifier: Topic :: Utilities
